fustor_common/__init__.py
fustor_common/daemon.py
fustor_common/daemon_launcher.py
fustor_common/enums.py
fustor_common/exceptions.py
fustor_common/logging_config.py
fustor_common/models.py
fustor_common/paths.py
fustor_common/schemas.py
fustor_common-0.2.16.dist-info/METADATA
fustor_common-0.2.16.dist-info/WHEEL
fustor_common-0.2.16.dist-info/top_level.txt
fustor_common-0.2.16.dist-info/RECORD
