Metadata-Version: 2.4
Name: fustor-common
Version: 0.2.16
Summary: Common utilities and models for Fustor services
License-Expression: MIT
Requires-Python: >=3.11
Requires-Dist: colorlog>=6.10.1
Requires-Dist: pydantic>=2.11.7
Requires-Dist: pydantic-settings>=2.3.4
